gui_win.py
timetable_to_calendar_zjnu.py
timetable_to_calendar_zjnu-1.0.1.dist-info/licenses/LICENSE
timetable_to_calendar_zjnu-1.0.1.dist-info/METADATA
timetable_to_calendar_zjnu-1.0.1.dist-info/WHEEL
timetable_to_calendar_zjnu-1.0.1.dist-info/entry_points.txt
timetable_to_calendar_zjnu-1.0.1.dist-info/top_level.txt
timetable_to_calendar_zjnu-1.0.1.dist-info/RECORD
