Metadata-Version: 2.4
Name: timetable-to-calendar-zjnu
Version: 1.0.1
Summary: Convert ZJNU timetable PDFs to iCalendar (.ics).
Author: Al-rimi
License: MIT License
Project-URL: Homepage, https://github.com/Al-rimi/Timetable-to-Calendar
Project-URL: Issues, https://github.com/Al-rimi/Timetable-to-Calendar/issues
Project-URL: Changelog, https://github.com/Al-rimi/Timetable-to-Calendar/blob/main/CHANGELOG.md
Keywords: ZJNU,calendar,ics,timetable,pdf
Classifier: Programming Language :: Python :: 3
Classifier: Programming Language :: Python :: 3 :: Only
Classifier: License :: OSI Approved :: MIT License
Classifier: Operating System :: OS Independent
Classifier: Environment :: Win32 (MS Windows)
Classifier: Environment :: MacOS X
Classifier: Environment :: X11 Applications
Requires-Python: >=3.10
License-File: LICENSE
Requires-Dist: pdfplumber
Requires-Dist: ics
Requires-Dist: tkinterdnd2
Dynamic: license-file
